{
  "videos": [
    {
      "id": 1,
      "videoUrl": "https://www.youtube.com/watch?v=oTe4f-bBEKg",
      "title": "BTS speech at the United Nations 2018 | UNICEF",
      "speaker": "BTS Namjoon"
    },
    {
      "id": 2,
      "videoUrl": "https://www.youtube.com/watch?v=vVs710bHkNA",
      "title": "BTS MAMA 2018 Artist of the year Full speech",
      "speaker": "BTS"
    },
    {
      "id": 3,
      "videoUrl": "https://www.youtube.com/watch?v=YqYlBeZEQak",
      "title": "BTS UN General Assembly 2018 Behind the scenes ",
      "speaker": "BTS"
    },
    {
      "id": 4,
      "videoUrl": "https://www.youtube.com/watch?v=kIKPZTZC4fI",
      "title": "BTS Wins Top Social Artists- BBMA 2017",
      "speaker": "RM"
    },
    {
      "id": 5,
      "videoUrl": "https://www.youtube.com/watch?v=b49c7A741iw",
      "title": "(BTS) @ Billboard Music Awards 2017",
      "speaker": "BTS"
    },
    {
      "id": 6,
      "videoUrl": "https://www.youtube.com/watch?v=bfDSAG60KcM",
      "title": " Backstage Reaction | Billboard Music Awards 2017",
      "speaker": "RM"
    },
    {
      "id": 7,
      "videoUrl": "https://www.youtube.com/watch?v=pE7Hjuz8LCM",
      "title": "BTS Wins Top Duo / Group - BBMAs 2019",
      "speaker": "BTS"
    },
    {
      "id": 8,
      "videoUrl": "https://www.youtube.com/watch?v=9Dfw8Ly2luo",
      "title": "BTS @ Billboard Music Awards 2019",
      "speaker": "BTS and Halsey"
    },
    {
      "id": 9,
      "videoUrl": "https://www.youtube.com/watch?v=pqdVRlcSJl0",
      "title": "BTS Wins Top Duo / Group - BBMAs 2018",
      "speaker": "BTS"
    },
    {
      "id": 10,
      "videoUrl": "https://www.youtube.com/watch?v=XnUIGjXj0fg",
      "title": "BTS @ Billboard Music Awards 2018",
      "speaker": "BTS"
    },
    {
      "id": 11,
      "videoUrl": "https://www.youtube.com/watch?v=pG4d1V8DfTc",
      "title": "BTS @2018 MAMA in JAPAN",
      "speaker": "BTS"
    },
    {
      "id": 12,
      "videoUrl": "https://www.youtube.com/watch?v=qcP3Nyld270",
      "title": "BTS at MAMA 2017 (Thank You Stage)",
      "speaker": "BTS"
    },
    {
      "id": 13,
      "videoUrl": "https://www.youtube.com/watch?v=XybcmNobpQg",
      "title": "BTS @ AMAs 2017",
      "speaker": "BTS"
    },
    {
      "id": 14,
      "videoUrl": "https://www.youtube.com/watch?v=3YPccm7Wnkw",
      "title": " BTS @2017 BTS MMA",
      "speaker": "BTS"
    },
    {
      "id": 15,
      "videoUrl": "https://www.youtube.com/watch?v=UZ_9b0dyl0Q",
      "title": "BTS MMA 2018 - FULL PERFORMANCE",
      "speaker": "BTS"
    },
    {
      "id": 16,
      "videoUrl": "https://www.youtube.com/watch?v=scVt3DEM0TM",
      "title": "@Seoul Music Awards 2019",
      "speaker": "BTS"
    },
    {
      "id": 17,
      "videoUrl": "https://www.youtube.com/watch?v=Qrcr4gJWehU",
      "title": "2019 MAMA ",
      "speaker": "BTS"
    },
    {
      "id": 18,
      "videoUrl": "https://www.youtube.com/watch?v=b9cG4DzpL_c",
      "title": "(BTS) | Full Live Performance MMA 2019",
      "speaker": "BTS"
    },
    {
      "id": 19,
      "videoUrl": "https://www.youtube.com/watch?v=AU6uF5sFtwA",
      "title": "BTS Commencement Speech | Dear Class Of 2020",
      "speaker": "BTS"
    },
    {
      "id": 20,
      "videoUrl": "https://www.youtube.com/watch?v=E3VEiruE3cM",
      "title": "BTS Artist of the Year Acceptance Speech MMA 2018",
      "speaker": "BTS"
    },
    {
      "id": 21,
      "videoUrl": "https://www.youtube.com/watch?v=8d9CBEriek0",
      "title": "BTS at 2020 MAMA",
      "speaker": "BTS"
    },
    {
      "id": 22,
      "videoUrl": "https://www.youtube.com/watch?v=s8lBFPLLgqA",
      "title": "2020 MMA BTS Speech",
      "speaker": "BTS"
    },
    {
      "id": 23,
      "videoUrl": "https://www.youtube.com/watch?v=wAXcMD5dOBA",
      "title": "BTS as Envoys of the President of the Republic of Korea at UN",
      "speaker": "BTS and the President of SK"
    },
    {
      "id": 24,
      "videoUrl": "https://www.youtube.com/watch?v=jzptPcPLCnA",
      "title": "President Moon Jae-in & BTS at the Sustainable Development Goals Moment UN",
      "speaker": "BTS & the President"
    },
    {
      "id": 25,
      "videoUrl": "https://www.youtube.com/watch?v=5aPe9Uy10n4",
      "title": "Speech at the 75th UN General Assembly",
      "speaker": "BTS"
    }
  ]
}
